psenv/__init__.py
psenv/__main__.py
psenv/cli/__init__.py
psenv/cli/destroy.py
psenv/cli/fetch.py
psenv/cli/init.py
psenv/cli/inject.py
psenv/cli/new.py
psenv/cli/push.py
psenv/cli/show.py
psenv/cli/validation.py
psenv/cli/version.py
psenv/core/config_file.py
psenv/core/env_file.py
psenv/core/parameter_store.py
psenv/environment/config.py
psenv/environment/variables.py
psenv/utils/cli.py
psenv-0.17.1.dist-info/METADATA
psenv-0.17.1.dist-info/WHEEL
psenv-0.17.1.dist-info/entry_points.txt
psenv-0.17.1.dist-info/top_level.txt
psenv-0.17.1.dist-info/RECORD
